rapidvalidators/__init__.py
rapidvalidators/_rapidvalidators.cpython-313-x86_64-linux-gnu.so
rapidvalidators-0.1.0.dist-info/METADATA
rapidvalidators-0.1.0.dist-info/WHEEL
rapidvalidators-0.1.0.dist-info/RECORD
